httpony/__init__.py
httpony/application.py
httpony/server.py
httpony/tests/__init__.py
httpony/tests/test_parser.py
httpony/tests/test_server.py
httpony-0.3.dist-info/LICENSE
httpony-0.3.dist-info/METADATA
httpony-0.3.dist-info/WHEEL
httpony-0.3.dist-info/entry_points.txt
httpony-0.3.dist-info/pbr.json
httpony-0.3.dist-info/top_level.txt
httpony-0.3.dist-info/RECORD
